myLib/__init__.py
myLib/datastructures/__init__.py
myLib/datastructures/Heap/Heap.py
myLib/datastructures/Heap/MaxH.py
myLib/datastructures/Heap/MinH.py
myLib/datastructures/Heap/__init__.py
myLib/datastructures/Linear/CDLL.py
myLib/datastructures/Linear/CSLL.py
myLib/datastructures/Linear/DLL.py
myLib/datastructures/Linear/QueueLL.py
myLib/datastructures/Linear/SLL.py
myLib/datastructures/Linear/StackLL.py
myLib/datastructures/Linear/__init__.py
myLib/datastructures/nodes/DNode.py
myLib/datastructures/nodes/SNode.py
myLib/datastructures/nodes/TNode.py
myLib/datastructures/nodes/__init__.py
myLib/datastructures/trees/AVL.py
myLib/datastructures/trees/BST.py
myLib/datastructures/trees/__init__.py
myLib/graphalgo/BFS.py
myLib/graphalgo/DFS.py
myLib/graphalgo/Djikstra.py
myLib/graphalgo/__init__.py
myLib/graphalgo/graph.py
Rodmichael_Marcus_338_package_bonus-1.0.dist-info/METADATA
Rodmichael_Marcus_338_package_bonus-1.0.dist-info/WHEEL
Rodmichael_Marcus_338_package_bonus-1.0.dist-info/top_level.txt
Rodmichael_Marcus_338_package_bonus-1.0.dist-info/RECORD
