Metadata-Version: 2.1
Name: Rodmichael-Marcus-338-package-bonus
Version: 1.0
Summary: Package containing Linear, nodes, trees, heaps and graph algorithms
Author: Rodmichael, Marcus
Author-email: rodmichael.umapas@ucalgary.ca, marcus.kittelson@ucalgary.ca
License: UNKNOWN
Platform: UNKNOWN
